SimpleOUCH/Parser.py
SimpleOUCH/__init__.py
simpleouch-0.0.2.dist-info/METADATA
simpleouch-0.0.2.dist-info/WHEEL
simpleouch-0.0.2.dist-info/licenses/LICENSE
simpleouch-0.0.2.dist-info/RECORD
