Metadata-Version: 2.1
Name: SimpleOUCH
Version: 0.0.2
Summary: A simple OUCH 5.0 parser
Project-URL: Homepage, https://github.com/pjfort/OUCH_Parser
Author-email: Peter Fortuna <peter.j.fortuna@gmail.com>
License-File: LICENSE
Classifier: License :: OSI Approved :: MIT License
Classifier: Operating System :: OS Independent
Classifier: Programming Language :: Python :: 3
Requires-Python: >=3.7
